README.rst
setup.py
blackhole/__init__.py
blackhole/decorators.py
blackhole/models.py
blackhole/urls.py
blackhole/utils.py
blackhole/views.py
django_blackhole.egg-info/PKG-INFO
django_blackhole.egg-info/SOURCES.txt
django_blackhole.egg-info/dependency_links.txt
django_blackhole.egg-info/top_level.txt