Metadata-Version: 1.1
Name: django-blackhole
Version: 0.1.7
Summary: Django application that let's you work in your templates apart from having or not the
